cal_gitlab_mirror/__main__.py
cal_gitlab_mirror/argbuilder.py
cal_gitlab_mirror/cli.py
cal_gitlab_mirror/config.py
cal_gitlab_mirror/constants.py
cal_gitlab_mirror/exec.py
cal_gitlab_mirror/git_ops.py
cal_gitlab_mirror/gitlab_api.py
cal_gitlab_mirror/mirror_read.py
cal_gitlab_mirror/mirror_write.py
cal_gitlab_mirror/version.py
cal_gitlab_mirror-0.3.0.dist-info/METADATA
cal_gitlab_mirror-0.3.0.dist-info/WHEEL
cal_gitlab_mirror-0.3.0.dist-info/entry_points.txt
cal_gitlab_mirror-0.3.0.dist-info/licenses/LICENSE
cal_gitlab_mirror-0.3.0.dist-info/RECORD
